<?xml version="1.0" encoding="UTF-8"?>
<inforef>
  <userref>
    <user>
      <id>27818</id>
    </user>
    <user>
      <id>28288</id>
    </user>
  </userref>
  <fileref>
    <file>
      <id>244345</id>
    </file>
    <file>
      <id>244346</id>
    </file>
    <file>
      <id>244347</id>
    </file>
    <file>
      <id>244348</id>
    </file>
    <file>
      <id>244349</id>
    </file>
    <file>
      <id>246333</id>
    </file>
    <file>
      <id>246334</id>
    </file>
    <file>
      <id>246335</id>
    </file>
    <file>
      <id>246336</id>
    </file>
    <file>
      <id>246337</id>
    </file>
    <file>
      <id>246338</id>
    </file>
    <file>
      <id>246339</id>
    </file>
    <file>
      <id>246340</id>
    </file>
    <file>
      <id>246341</id>
    </file>
    <file>
      <id>246342</id>
    </file>
    <file>
      <id>246343</id>
    </file>
    <file>
      <id>246344</id>
    </file>
    <file>
      <id>246345</id>
    </file>
    <file>
      <id>246346</id>
    </file>
    <file>
      <id>246347</id>
    </file>
    <file>
      <id>246348</id>
    </file>
    <file>
      <id>246349</id>
    </file>
    <file>
      <id>246350</id>
    </file>
    <file>
      <id>246351</id>
    </file>
    <file>
      <id>246352</id>
    </file>
    <file>
      <id>246353</id>
    </file>
    <file>
      <id>246354</id>
    </file>
    <file>
      <id>246355</id>
    </file>
    <file>
      <id>246356</id>
    </file>
    <file>
      <id>246357</id>
    </file>
    <file>
      <id>246358</id>
    </file>
  </fileref>
</inforef>